{
  "errors": [],
  "events": [
    {
      "comp_id": 4,
      "alarm_id": null,
      "start": "2003-01-09T00:00:00+13:00",
      "end": "2003-01-10T00:00:00+13:00"
    },
    {
      "comp_id": 5,
      "alarm_id": null,
      "start": "2003-01-16T00:00:00+13:00",
      "end": "2003-01-17T00:00:00+13:00"
    },
    {
      "comp_id": 6,
      "alarm_id": null,
      "start": "2003-01-16T00:00:00+13:00",
      "end": "2003-01-17T00:00:00+13:00"
    },
    {
      "comp_id": 7,
      "alarm_id": null,
      "start": "2003-01-16T00:00:00+13:00",
      "end": "2003-01-17T00:00:00+13:00"
    },
    {
      "comp_id": 8,
      "alarm_id": null,
      "start": "2003-01-23T00:00:00+13:00",
      "end": "2003-01-24T00:00:00+13:00"
    },
    {
      "comp_id": 40,
      "alarm_id": null,
      "start": "2003-07-31T23:00:00+10:00",
      "end": "2003-08-01T00:00:00+10:00"
    },
    {
      "comp_id": 41,
      "alarm_id": null,
      "start": "2003-07-31T23:00:00+10:00",
      "end": "2003-08-01T00:00:00+10:00"
    },
    {
      "comp_id": 42,
      "alarm_id": null,
      "start": "2003-07-31T23:00:00+10:00",
      "end": "2003-08-01T00:00:00+10:00"
    },
    {
      "comp_id": 10,
      "alarm_id": null,
      "start": "2003-08-28T00:00:00+12:00",
      "end": "2003-08-29T00:00:00+12:00"
    },
    {
      "comp_id": 11,
      "alarm_id": null,
      "start": "2003-08-28T00:00:00+12:00",
      "end": "2003-08-29T00:00:00+12:00"
    },
    {
      "comp_id": 12,
      "alarm_id": null,
      "start": "2003-08-28T00:00:00+12:00",
      "end": "2003-08-29T00:00:00+12:00"
    },
    {
      "comp_id": 66,
      "alarm_id": null,
      "start": "2003-08-28T00:00:00+12:00",
      "end": "2003-08-29T00:00:00+12:00"
    },
    {
      "comp_id": 13,
      "alarm_id": null,
      "start": "2003-09-04T00:00:00+12:00",
      "end": "2003-09-05T00:00:00+12:00"
    },
    {
      "comp_id": 14,
      "alarm_id": null,
      "start": "2003-09-04T00:00:00+12:00",
      "end": "2003-09-05T00:00:00+12:00"
    },
    {
      "comp_id": 23,
      "alarm_id": null,
      "start": "2003-09-04T00:00:00+12:00",
      "end": "2003-09-05T00:00:00+12:00"
    },
    {
      "comp_id": 80,
      "alarm_id": null,
      "start": "2003-09-10T11:15:00+10:00",
      "end": "2003-09-10T12:15:00+10:00"
    },
    {
      "comp_id": 15,
      "alarm_id": null,
      "start": "2003-09-11T00:00:00+12:00",
      "end": "2003-09-12T00:00:00+12:00"
    },
    {
      "comp_id": 16,
      "alarm_id": null,
      "start": "2003-09-11T00:00:00+12:00",
      "end": "2003-09-12T00:00:00+12:00"
    },
    {
      "comp_id": 17,
      "alarm_id": null,
      "start": "2003-09-18T00:00:00+12:00",
      "end": "2003-09-19T00:00:00+12:00"
    },
    {
      "comp_id": 18,
      "alarm_id": null,
      "start": "2003-09-25T00:00:00+12:00",
      "end": "2003-09-26T00:00:00+12:00"
    },
    {
      "comp_id": 19,
      "alarm_id": null,
      "start": "2003-09-25T00:00:00+12:00",
      "end": "2003-09-26T00:00:00+12:00"
    },
    {
      "comp_id": 21,
      "alarm_id": null,
      "start": "2003-09-25T00:00:00+12:00",
      "end": "2003-09-26T00:00:00+12:00"
    },
    {
      "comp_id": 43,
      "alarm_id": null,
      "start": "2003-09-25T00:00:00+12:00",
      "end": "2003-09-26T00:00:00+12:00"
    },
    {
      "comp_id": 44,
      "alarm_id": null,
      "start": "2003-09-25T00:00:00+12:00",
      "end": "2003-09-26T00:00:00+12:00"
    },
    {
      "comp_id": 9,
      "alarm_id": null,
      "start": "2003-10-02T00:00:00+12:00",
      "end": "2003-10-03T00:00:00+12:00"
    },
    {
      "comp_id": 24,
      "alarm_id": null,
      "start": "2003-10-02T00:00:00+12:00",
      "end": "2003-10-03T00:00:00+12:00"
    },
    {
      "comp_id": 45,
      "alarm_id": null,
      "start": "2003-10-09T00:00:00+13:00",
      "end": "2003-10-10T00:00:00+13:00"
    },
    {
      "comp_id": 81,
      "alarm_id": null,
      "start": "2003-10-09T00:00:00+13:00",
      "end": "2003-10-10T00:00:00+13:00"
    },
    {
      "comp_id": 25,
      "alarm_id": null,
      "start": "2003-10-16T00:00:00+13:00",
      "end": "2003-10-17T00:00:00+13:00"
    },
    {
      "comp_id": 27,
      "alarm_id": null,
      "start": "2003-10-16T00:00:00+13:00",
      "end": "2003-10-17T00:00:00+13:00"
    },
    {
      "comp_id": 28,
      "alarm_id": null,
      "start": "2003-10-16T00:00:00+13:00",
      "end": "2003-10-17T00:00:00+13:00"
    },
    {
      "comp_id": 96,
      "alarm_id": null,
      "start": "2003-10-18T00:00:00+10:00",
      "end": "2003-10-18T23:59:59+10:00"
    },
    {
      "comp_id": 29,
      "alarm_id": null,
      "start": "2003-10-23T00:00:00+13:00",
      "end": "2003-10-24T00:00:00+13:00"
    },
    {
      "comp_id": 30,
      "alarm_id": null,
      "start": "2003-10-23T00:00:00+13:00",
      "end": "2003-10-24T00:00:00+13:00"
    },
    {
      "comp_id": 84,
      "alarm_id": null,
      "start": "2003-10-23T00:00:00+13:00",
      "end": "2003-10-24T00:00:00+13:00"
    },
    {
      "comp_id": 97,
      "alarm_id": null,
      "start": "2003-10-23T00:00:00+13:00",
      "end": "2003-10-24T00:00:00+13:00"
    },
    {
      "comp_id": 98,
      "alarm_id": null,
      "start": "2003-10-23T00:00:00+10:00",
      "end": "2003-10-23T23:59:59+10:00"
    },
    {
      "comp_id": 31,
      "alarm_id": null,
      "start": "2003-10-30T00:00:00+13:00",
      "end": "2003-10-31T00:00:00+13:00"
    },
    {
      "comp_id": 32,
      "alarm_id": null,
      "start": "2003-10-30T00:00:00+13:00",
      "end": "2003-10-31T00:00:00+13:00"
    },
    {
      "comp_id": 47,
      "alarm_id": null,
      "start": "2003-10-30T00:00:00+13:00",
      "end": "2003-10-31T00:00:00+13:00"
    },
    {
      "comp_id": 85,
      "alarm_id": null,
      "start": "2003-10-30T00:00:00+13:00",
      "end": "2003-10-31T00:00:00+13:00"
    },
    {
      "comp_id": 86,
      "alarm_id": null,
      "start": "2003-10-30T00:00:00+13:00",
      "end": "2003-10-31T00:00:00+13:00"
    },
    {
      "comp_id": 87,
      "alarm_id": null,
      "start": "2003-10-30T00:00:00+13:00",
      "end": "2003-10-31T00:00:00+13:00"
    },
    {
      "comp_id": 22,
      "alarm_id": null,
      "start": "2003-11-06T00:00:00+13:00",
      "end": "2003-11-07T00:00:00+13:00"
    },
    {
      "comp_id": 26,
      "alarm_id": null,
      "start": "2003-11-06T00:00:00+13:00",
      "end": "2003-11-07T00:00:00+13:00"
    },
    {
      "comp_id": 48,
      "alarm_id": null,
      "start": "2003-11-06T00:00:00+13:00",
      "end": "2003-11-07T00:00:00+13:00"
    },
    {
      "comp_id": 35,
      "alarm_id": null,
      "start": "2003-11-13T00:00:00+13:00",
      "end": "2003-11-14T00:00:00+13:00"
    },
    {
      "comp_id": 36,
      "alarm_id": null,
      "start": "2003-11-13T00:00:00+13:00",
      "end": "2003-11-14T00:00:00+13:00"
    },
    {
      "comp_id": 88,
      "alarm_id": null,
      "start": "2003-11-13T00:00:00+13:00",
      "end": "2003-11-14T00:00:00+13:00"
    },
    {
      "comp_id": 90,
      "alarm_id": null,
      "start": "2003-11-13T00:00:00+13:00",
      "end": "2003-11-14T00:00:00+13:00"
    },
    {
      "comp_id": 34,
      "alarm_id": null,
      "start": "2003-11-20T00:00:00+13:00",
      "end": "2003-11-21T00:00:00+13:00"
    },
    {
      "comp_id": 37,
      "alarm_id": null,
      "start": "2003-11-20T00:00:00+13:00",
      "end": "2003-11-21T00:00:00+13:00"
    },
    {
      "comp_id": 38,
      "alarm_id": null,
      "start": "2003-11-20T00:00:00+13:00",
      "end": "2003-11-21T00:00:00+13:00"
    },
    {
      "comp_id": 49,
      "alarm_id": null,
      "start": "2003-11-20T00:00:00+13:00",
      "end": "2003-11-21T00:00:00+13:00"
    },
    {
      "comp_id": 64,
      "alarm_id": null,
      "start": "2003-11-20T00:00:00+13:00",
      "end": "2003-11-21T00:00:00+13:00"
    },
    {
      "comp_id": 91,
      "alarm_id": null,
      "start": "2003-11-20T00:00:00+13:00",
      "end": "2003-11-21T00:00:00+13:00"
    },
    {
      "comp_id": 113,
      "alarm_id": null,
      "start": "2003-11-26T00:00:00+11:00",
      "end": "2003-11-26T23:59:59+11:00"
    },
    {
      "comp_id": 33,
      "alarm_id": null,
      "start": "2003-11-27T00:00:00+13:00",
      "end": "2003-11-28T00:00:00+13:00"
    },
    {
      "comp_id": 52,
      "alarm_id": null,
      "start": "2003-11-27T00:00:00+13:00",
      "end": "2003-11-28T00:00:00+13:00"
    },
    {
      "comp_id": 67,
      "alarm_id": null,
      "start": "2003-11-27T00:00:00+13:00",
      "end": "2003-11-28T00:00:00+13:00"
    },
    {
      "comp_id": 53,
      "alarm_id": null,
      "start": "2003-12-04T00:00:00+13:00",
      "end": "2003-12-05T00:00:00+13:00"
    },
    {
      "comp_id": 82,
      "alarm_id": null,
      "start": "2003-12-04T00:00:00+13:00",
      "end": "2003-12-05T00:00:00+13:00"
    },
    {
      "comp_id": 20,
      "alarm_id": null,
      "start": "2003-12-11T00:00:00+13:00",
      "end": "2003-12-12T00:00:00+13:00"
    },
    {
      "comp_id": 54,
      "alarm_id": null,
      "start": "2003-12-11T00:00:00+13:00",
      "end": "2003-12-12T00:00:00+13:00"
    },
    {
      "comp_id": 68,
      "alarm_id": null,
      "start": "2003-12-11T00:00:00+13:00",
      "end": "2003-12-12T00:00:00+13:00"
    },
    {
      "comp_id": 78,
      "alarm_id": null,
      "start": "2003-12-11T00:00:00+13:00",
      "end": "2003-12-12T00:00:00+13:00"
    },
    {
      "comp_id": 92,
      "alarm_id": null,
      "start": "2003-12-11T00:00:00+13:00",
      "end": "2003-12-12T00:00:00+13:00"
    },
    {
      "comp_id": 58,
      "alarm_id": null,
      "start": "2003-12-18T00:00:00+13:00",
      "end": "2003-12-19T00:00:00+13:00"
    },
    {
      "comp_id": 79,
      "alarm_id": null,
      "start": "2003-12-18T00:00:00+13:00",
      "end": "2003-12-19T00:00:00+13:00"
    },
    {
      "comp_id": 39,
      "alarm_id": null,
      "start": "2003-12-26T00:00:00+13:00",
      "end": "2003-12-27T00:00:00+13:00"
    },
    {
      "comp_id": 56,
      "alarm_id": null,
      "start": "2003-12-26T00:00:00+13:00",
      "end": "2003-12-27T00:00:00+13:00"
    },
    {
      "comp_id": 57,
      "alarm_id": null,
      "start": "2003-12-26T00:00:00+13:00",
      "end": "2003-12-27T00:00:00+13:00"
    },
    {
      "comp_id": 89,
      "alarm_id": null,
      "start": "2003-12-26T00:00:00+13:00",
      "end": "2003-12-27T00:00:00+13:00"
    },
    {
      "comp_id": 93,
      "alarm_id": null,
      "start": "2003-12-26T00:00:00+13:00",
      "end": "2003-12-27T00:00:00+13:00"
    },
    {
      "comp_id": 55,
      "alarm_id": null,
      "start": "2004-01-01T00:00:00+13:00",
      "end": "2004-01-02T00:00:00+13:00"
    },
    {
      "comp_id": 59,
      "alarm_id": null,
      "start": "2004-01-01T00:00:00+13:00",
      "end": "2004-01-02T00:00:00+13:00"
    },
    {
      "comp_id": 60,
      "alarm_id": null,
      "start": "2004-01-01T00:00:00+13:00",
      "end": "2004-01-02T00:00:00+13:00"
    },
    {
      "comp_id": 62,
      "alarm_id": null,
      "start": "2004-01-08T00:00:00+13:00",
      "end": "2004-01-09T00:00:00+13:00"
    },
    {
      "comp_id": 70,
      "alarm_id": null,
      "start": "2004-01-08T00:00:00+13:00",
      "end": "2004-01-09T00:00:00+13:00"
    },
    {
      "comp_id": 72,
      "alarm_id": null,
      "start": "2004-01-08T00:00:00+13:00",
      "end": "2004-01-09T00:00:00+13:00"
    },
    {
      "comp_id": 61,
      "alarm_id": null,
      "start": "2004-01-15T00:00:00+13:00",
      "end": "2004-01-16T00:00:00+13:00"
    },
    {
      "comp_id": 75,
      "alarm_id": null,
      "start": "2004-01-15T00:00:00+13:00",
      "end": "2004-01-16T00:00:00+13:00"
    },
    {
      "comp_id": 99,
      "alarm_id": null,
      "start": "2004-01-15T00:00:00+13:00",
      "end": "2004-01-16T00:00:00+13:00"
    },
    {
      "comp_id": 46,
      "alarm_id": null,
      "start": "2004-01-22T00:00:00+13:00",
      "end": "2004-01-23T00:00:00+13:00"
    },
    {
      "comp_id": 76,
      "alarm_id": null,
      "start": "2004-01-22T00:00:00+13:00",
      "end": "2004-01-23T00:00:00+13:00"
    },
    {
      "comp_id": 83,
      "alarm_id": null,
      "start": "2004-01-22T00:00:00+13:00",
      "end": "2004-01-23T00:00:00+13:00"
    },
    {
      "comp_id": 95,
      "alarm_id": null,
      "start": "2004-01-22T00:00:00+13:00",
      "end": "2004-01-23T00:00:00+13:00"
    },
    {
      "comp_id": 125,
      "alarm_id": null,
      "start": "2004-01-22T00:00:00+13:00",
      "end": "2004-01-23T00:00:00+13:00"
    },
    {
      "comp_id": 63,
      "alarm_id": null,
      "start": "2004-01-29T00:00:00+13:00",
      "end": "2004-01-30T00:00:00+13:00"
    },
    {
      "comp_id": 77,
      "alarm_id": null,
      "start": "2004-01-29T00:00:00+13:00",
      "end": "2004-01-30T00:00:00+13:00"
    },
    {
      "comp_id": 111,
      "alarm_id": null,
      "start": "2004-01-29T00:00:00+13:00",
      "end": "2004-01-30T00:00:00+13:00"
    },
    {
      "comp_id": 112,
      "alarm_id": null,
      "start": "2004-02-03T00:00:00+11:00",
      "end": "2004-02-03T23:59:59+11:00"
    },
    {
      "comp_id": 69,
      "alarm_id": null,
      "start": "2004-02-05T00:00:00+13:00",
      "end": "2004-02-06T00:00:00+13:00"
    },
    {
      "comp_id": 71,
      "alarm_id": null,
      "start": "2004-02-05T00:00:00+13:00",
      "end": "2004-02-06T00:00:00+13:00"
    },
    {
      "comp_id": 101,
      "alarm_id": null,
      "start": "2004-02-05T00:00:00+13:00",
      "end": "2004-02-06T00:00:00+13:00"
    },
    {
      "comp_id": 119,
      "alarm_id": null,
      "start": "2004-02-05T00:00:00+13:00",
      "end": "2004-02-06T00:00:00+13:00"
    },
    {
      "comp_id": 74,
      "alarm_id": null,
      "start": "2004-02-12T00:00:00+13:00",
      "end": "2004-02-13T00:00:00+13:00"
    },
    {
      "comp_id": 103,
      "alarm_id": null,
      "start": "2004-02-12T00:00:00+13:00",
      "end": "2004-02-13T00:00:00+13:00"
    },
    {
      "comp_id": 104,
      "alarm_id": null,
      "start": "2004-02-12T00:00:00+13:00",
      "end": "2004-02-13T00:00:00+13:00"
    },
    {
      "comp_id": 105,
      "alarm_id": null,
      "start": "2004-02-12T00:00:00+13:00",
      "end": "2004-02-13T00:00:00+13:00"
    },
    {
      "comp_id": 106,
      "alarm_id": null,
      "start": "2004-02-12T00:00:00+13:00",
      "end": "2004-02-13T00:00:00+13:00"
    },
    {
      "comp_id": 114,
      "alarm_id": null,
      "start": "2004-02-12T00:00:00+13:00",
      "end": "2004-02-13T00:00:00+13:00"
    },
    {
      "comp_id": 50,
      "alarm_id": null,
      "start": "2004-02-19T00:00:00+13:00",
      "end": "2004-02-20T00:00:00+13:00"
    },
    {
      "comp_id": 51,
      "alarm_id": null,
      "start": "2004-02-19T00:00:00+13:00",
      "end": "2004-02-20T00:00:00+13:00"
    },
    {
      "comp_id": 100,
      "alarm_id": null,
      "start": "2004-02-19T00:00:00+13:00",
      "end": "2004-02-20T00:00:00+13:00"
    },
    {
      "comp_id": 107,
      "alarm_id": null,
      "start": "2004-02-19T00:00:00+13:00",
      "end": "2004-02-20T00:00:00+13:00"
    },
    {
      "comp_id": 110,
      "alarm_id": null,
      "start": "2004-02-19T00:00:00+13:00",
      "end": "2004-02-20T00:00:00+13:00"
    },
    {
      "comp_id": 159,
      "alarm_id": null,
      "start": "2004-02-19T00:00:00+11:00",
      "end": "2004-02-19T01:00:00+11:00"
    },
    {
      "comp_id": 117,
      "alarm_id": null,
      "start": "2004-02-25T00:00:00+13:00",
      "end": "2004-02-26T00:00:00+13:00"
    },
    {
      "comp_id": 73,
      "alarm_id": null,
      "start": "2004-02-26T00:00:00+13:00",
      "end": "2004-02-27T00:00:00+13:00"
    },
    {
      "comp_id": 109,
      "alarm_id": null,
      "start": "2004-02-26T00:00:00+13:00",
      "end": "2004-02-27T00:00:00+13:00"
    },
    {
      "comp_id": 138,
      "alarm_id": null,
      "start": "2004-02-26T00:00:00+13:00",
      "end": "2004-02-27T00:00:00+13:00"
    },
    {
      "comp_id": 155,
      "alarm_id": null,
      "start": "2004-02-26T00:00:00+13:00",
      "end": "2004-02-27T00:00:00+13:00"
    },
    {
      "comp_id": 94,
      "alarm_id": null,
      "start": "2004-03-04T00:00:00+13:00",
      "end": "2004-03-05T00:00:00+13:00"
    },
    {
      "comp_id": 108,
      "alarm_id": null,
      "start": "2004-03-04T00:00:00+13:00",
      "end": "2004-03-05T00:00:00+13:00"
    },
    {
      "comp_id": 115,
      "alarm_id": null,
      "start": "2004-03-04T00:00:00+13:00",
      "end": "2004-03-05T00:00:00+13:00"
    },
    {
      "comp_id": 116,
      "alarm_id": null,
      "start": "2004-03-04T00:00:00+13:00",
      "end": "2004-03-05T00:00:00+13:00"
    },
    {
      "comp_id": 120,
      "alarm_id": null,
      "start": "2004-03-04T00:00:00+13:00",
      "end": "2004-03-05T00:00:00+13:00"
    },
    {
      "comp_id": 102,
      "alarm_id": null,
      "start": "2004-03-11T00:00:00+13:00",
      "end": "2004-03-12T00:00:00+13:00"
    },
    {
      "comp_id": 134,
      "alarm_id": null,
      "start": "2004-03-11T00:00:00+13:00",
      "end": "2004-03-12T00:00:00+13:00"
    },
    {
      "comp_id": 135,
      "alarm_id": null,
      "start": "2004-03-11T00:00:00+13:00",
      "end": "2004-03-12T00:00:00+13:00"
    },
    {
      "comp_id": 121,
      "alarm_id": null,
      "start": "2004-03-18T00:00:00+13:00",
      "end": "2004-03-19T00:00:00+13:00"
    },
    {
      "comp_id": 122,
      "alarm_id": null,
      "start": "2004-03-18T00:00:00+13:00",
      "end": "2004-03-19T00:00:00+13:00"
    },
    {
      "comp_id": 124,
      "alarm_id": null,
      "start": "2004-03-18T00:00:00+13:00",
      "end": "2004-03-19T00:00:00+13:00"
    },
    {
      "comp_id": 130,
      "alarm_id": null,
      "start": "2004-03-18T00:00:00+13:00",
      "end": "2004-03-19T00:00:00+13:00"
    },
    {
      "comp_id": 156,
      "alarm_id": null,
      "start": "2004-03-18T00:00:00+13:00",
      "end": "2004-03-19T00:00:00+13:00"
    },
    {
      "comp_id": 127,
      "alarm_id": null,
      "start": "2004-03-25T00:00:00+12:00",
      "end": "2004-03-26T00:00:00+12:00"
    },
    {
      "comp_id": 128,
      "alarm_id": null,
      "start": "2004-03-25T00:00:00+12:00",
      "end": "2004-03-26T00:00:00+12:00"
    },
    {
      "comp_id": 139,
      "alarm_id": null,
      "start": "2004-03-25T00:00:00+12:00",
      "end": "2004-03-26T00:00:00+12:00"
    },
    {
      "comp_id": 144,
      "alarm_id": null,
      "start": "2004-03-25T00:00:00+12:00",
      "end": "2004-03-26T00:00:00+12:00"
    },
    {
      "comp_id": 152,
      "alarm_id": null,
      "start": "2004-03-25T00:00:00+12:00",
      "end": "2004-03-26T00:00:00+12:00"
    },
    {
      "comp_id": 126,
      "alarm_id": null,
      "start": "2004-04-01T00:00:00+12:00",
      "end": "2004-04-02T00:00:00+12:00"
    },
    {
      "comp_id": 129,
      "alarm_id": null,
      "start": "2004-04-01T00:00:00+12:00",
      "end": "2004-04-02T00:00:00+12:00"
    },
    {
      "comp_id": 145,
      "alarm_id": null,
      "start": "2004-04-01T00:00:00+12:00",
      "end": "2004-04-02T00:00:00+12:00"
    },
    {
      "comp_id": 118,
      "alarm_id": null,
      "start": "2004-04-08T00:00:00+12:00",
      "end": "2004-04-09T00:00:00+12:00"
    },
    {
      "comp_id": 132,
      "alarm_id": null,
      "start": "2004-04-08T00:00:00+12:00",
      "end": "2004-04-09T00:00:00+12:00"
    },
    {
      "comp_id": 133,
      "alarm_id": null,
      "start": "2004-04-08T00:00:00+12:00",
      "end": "2004-04-09T00:00:00+12:00"
    },
    {
      "comp_id": 146,
      "alarm_id": null,
      "start": "2004-04-08T00:00:00+12:00",
      "end": "2004-04-09T00:00:00+12:00"
    },
    {
      "comp_id": 175,
      "alarm_id": null,
      "start": "2004-04-08T00:00:00+12:00",
      "end": "2004-04-09T00:00:00+12:00"
    },
    {
      "comp_id": 131,
      "alarm_id": null,
      "start": "2004-04-15T00:00:00+12:00",
      "end": "2004-04-16T00:00:00+12:00"
    },
    {
      "comp_id": 140,
      "alarm_id": null,
      "start": "2004-04-15T00:00:00+12:00",
      "end": "2004-04-16T00:00:00+12:00"
    },
    {
      "comp_id": 147,
      "alarm_id": null,
      "start": "2004-04-15T00:00:00+12:00",
      "end": "2004-04-16T00:00:00+12:00"
    },
    {
      "comp_id": 136,
      "alarm_id": null,
      "start": "2004-04-22T00:00:00+12:00",
      "end": "2004-04-23T00:00:00+12:00"
    },
    {
      "comp_id": 137,
      "alarm_id": null,
      "start": "2004-04-22T00:00:00+12:00",
      "end": "2004-04-23T00:00:00+12:00"
    },
    {
      "comp_id": 141,
      "alarm_id": null,
      "start": "2004-04-22T00:00:00+12:00",
      "end": "2004-04-23T00:00:00+12:00"
    },
    {
      "comp_id": 148,
      "alarm_id": null,
      "start": "2004-04-22T00:00:00+12:00",
      "end": "2004-04-23T00:00:00+12:00"
    },
    {
      "comp_id": 123,
      "alarm_id": null,
      "start": "2004-04-29T00:00:00+12:00",
      "end": "2004-04-30T00:00:00+12:00"
    },
    {
      "comp_id": 142,
      "alarm_id": null,
      "start": "2004-04-29T00:00:00+12:00",
      "end": "2004-04-30T00:00:00+12:00"
    },
    {
      "comp_id": 143,
      "alarm_id": null,
      "start": "2004-04-29T00:00:00+12:00",
      "end": "2004-04-30T00:00:00+12:00"
    },
    {
      "comp_id": 149,
      "alarm_id": null,
      "start": "2004-04-29T00:00:00+12:00",
      "end": "2004-04-30T00:00:00+12:00"
    },
    {
      "comp_id": 180,
      "alarm_id": null,
      "start": "2004-04-29T00:00:00+12:00",
      "end": "2004-04-30T00:00:00+12:00"
    },
    {
      "comp_id": 150,
      "alarm_id": null,
      "start": "2004-05-06T00:00:00+12:00",
      "end": "2004-05-07T00:00:00+12:00"
    },
    {
      "comp_id": 160,
      "alarm_id": null,
      "start": "2004-05-06T00:00:00+12:00",
      "end": "2004-05-07T00:00:00+12:00"
    },
    {
      "comp_id": 165,
      "alarm_id": null,
      "start": "2004-05-06T00:00:00+12:00",
      "end": "2004-05-07T00:00:00+12:00"
    },
    {
      "comp_id": 153,
      "alarm_id": null,
      "start": "2004-05-13T00:00:00+12:00",
      "end": "2004-05-14T00:00:00+12:00"
    },
    {
      "comp_id": 154,
      "alarm_id": null,
      "start": "2004-05-13T00:00:00+12:00",
      "end": "2004-05-14T00:00:00+12:00"
    },
    {
      "comp_id": 157,
      "alarm_id": null,
      "start": "2004-05-20T00:00:00+12:00",
      "end": "2004-05-21T00:00:00+12:00"
    },
    {
      "comp_id": 158,
      "alarm_id": null,
      "start": "2004-05-20T00:00:00+12:00",
      "end": "2004-05-21T00:00:00+12:00"
    },
    {
      "comp_id": 181,
      "alarm_id": null,
      "start": "2004-05-20T00:00:00+12:00",
      "end": "2004-05-21T00:00:00+12:00"
    },
    {
      "comp_id": 161,
      "alarm_id": null,
      "start": "2004-05-27T00:00:00+12:00",
      "end": "2004-05-28T00:00:00+12:00"
    },
    {
      "comp_id": 162,
      "alarm_id": null,
      "start": "2004-05-27T00:00:00+12:00",
      "end": "2004-05-28T00:00:00+12:00"
    },
    {
      "comp_id": 163,
      "alarm_id": null,
      "start": "2004-05-27T00:00:00+12:00",
      "end": "2004-05-28T00:00:00+12:00"
    },
    {
      "comp_id": 164,
      "alarm_id": null,
      "start": "2004-06-03T00:00:00+12:00",
      "end": "2004-06-04T00:00:00+12:00"
    },
    {
      "comp_id": 169,
      "alarm_id": null,
      "start": "2004-06-03T00:00:00+12:00",
      "end": "2004-06-04T00:00:00+12:00"
    },
    {
      "comp_id": 170,
      "alarm_id": null,
      "start": "2004-06-03T00:00:00+12:00",
      "end": "2004-06-04T00:00:00+12:00"
    },
    {
      "comp_id": 167,
      "alarm_id": null,
      "start": "2004-06-10T00:00:00+12:00",
      "end": "2004-06-11T00:00:00+12:00"
    },
    {
      "comp_id": 168,
      "alarm_id": null,
      "start": "2004-06-10T00:00:00+12:00",
      "end": "2004-06-11T00:00:00+12:00"
    },
    {
      "comp_id": 151,
      "alarm_id": null,
      "start": "2004-06-17T00:00:00+12:00",
      "end": "2004-06-18T00:00:00+12:00"
    },
    {
      "comp_id": 172,
      "alarm_id": null,
      "start": "2004-06-17T00:00:00+12:00",
      "end": "2004-06-18T00:00:00+12:00"
    },
    {
      "comp_id": 173,
      "alarm_id": null,
      "start": "2004-06-24T00:00:00+12:00",
      "end": "2004-06-25T00:00:00+12:00"
    },
    {
      "comp_id": 174,
      "alarm_id": null,
      "start": "2004-06-24T00:00:00+12:00",
      "end": "2004-06-25T00:00:00+12:00"
    },
    {
      "comp_id": 176,
      "alarm_id": null,
      "start": "2004-06-24T00:00:00+12:00",
      "end": "2004-06-25T00:00:00+12:00"
    },
    {
      "comp_id": 177,
      "alarm_id": null,
      "start": "2004-06-24T00:00:00+12:00",
      "end": "2004-06-25T00:00:00+12:00"
    },
    {
      "comp_id": 182,
      "alarm_id": null,
      "start": "2004-06-24T00:00:00+12:00",
      "end": "2004-06-25T00:00:00+12:00"
    },
    {
      "comp_id": 178,
      "alarm_id": null,
      "start": "2004-07-01T00:00:00+12:00",
      "end": "2004-07-02T00:00:00+12:00"
    },
    {
      "comp_id": 179,
      "alarm_id": null,
      "start": "2004-07-01T00:00:00+12:00",
      "end": "2004-07-02T00:00:00+12:00"
    },
    {
      "comp_id": 183,
      "alarm_id": null,
      "start": "2004-07-08T00:00:00+12:00",
      "end": "2004-07-09T00:00:00+12:00"
    },
    {
      "comp_id": 184,
      "alarm_id": null,
      "start": "2004-07-08T00:00:00+12:00",
      "end": "2004-07-09T00:00:00+12:00"
    },
    {
      "comp_id": 185,
      "alarm_id": null,
      "start": "2004-07-08T00:00:00+12:00",
      "end": "2004-07-09T00:00:00+12:00"
    },
    {
      "comp_id": 186,
      "alarm_id": null,
      "start": "2004-07-15T00:00:00+12:00",
      "end": "2004-07-16T00:00:00+12:00"
    },
    {
      "comp_id": 187,
      "alarm_id": null,
      "start": "2004-07-15T00:00:00+12:00",
      "end": "2004-07-16T00:00:00+12:00"
    },
    {
      "comp_id": 188,
      "alarm_id": null,
      "start": "2004-07-22T00:00:00+12:00",
      "end": "2004-07-23T00:00:00+12:00"
    },
    {
      "comp_id": 189,
      "alarm_id": null,
      "start": "2004-07-22T00:00:00+12:00",
      "end": "2004-07-23T00:00:00+12:00"
    },
    {
      "comp_id": 166,
      "alarm_id": null,
      "start": "2004-08-12T00:00:00+12:00",
      "end": "2004-08-13T00:00:00+12:00"
    },
    {
      "comp_id": 171,
      "alarm_id": null,
      "start": "2004-09-16T00:00:00+12:00",
      "end": "2004-09-17T00:00:00+12:00"
    },
    {
      "comp_id": 65,
      "alarm_id": null,
      "start": "2004-12-26T00:00:00+13:00",
      "end": "2004-12-27T00:00:00+13:00"
    }
  ]
}
